bolos/__init__.py
bolos/grid.py
bolos/parse.py
bolos/parser.py
bolos/process.py
bolos/solver.py
bolos/target.py
bolos-0.2.dist-info/METADATA
bolos-0.2.dist-info/RECORD
bolos-0.2.dist-info/WHEEL
bolos-0.2.dist-info/top_level.txt
